{"version": 1.3, "people": [{"person_id": [-1], "pose_keypoints_2d": [0, 0, 0, 0, 0, 0, 1162.99, 392.025, 0.175894, 1160.12, 483.181, 0.325112, 1136.55, 553.879, 0.285461, 0, 0, 0, 0, 0, 0, 0, 0, 0, 0, 0, 0, 0, 0, 0, 0, 0, 0, 0, 0, 0, 0, 0, 0, 0, 0, 0, 0, 0, 0, 0, 0, 0, 0, 0, 0, 0, 0, 0, 0, 0, 0, 0, 0, 0, 0, 0, 0, 0, 0, 0, 0, 0, 0, 0, 0, 0, 0, 0, 0], "face_keypoints_2d": [], "hand_left_keypoints_2d": [], "hand_right_keypoints_2d": [], "pose_keypoints_3d": [], "face_keypoints_3d": [], "hand_left_keypoints_3d": [], "hand_right_keypoints_3d": []}]}